
{
   "allowSleep" : true,
   "autoClearForces" : true,
   "body" : 
   [
      
      {
         "angle" : 0,
         "angularVelocity" : 0,
         "awake" : true,
         "linearVelocity" : 0,
         "position" : 0,
         "type" : 0 //static
      },
      
      {
         "angle" : 0,
         "angularVelocity" : 0,
         "awake" : true,
         "linearVelocity" : 0,
         "position" : 0,
         "type" : 0 //static
      },
      
      {
         "angle" : 0,
         "angularVelocity" : 0,
         "awake" : true,
         "linearVelocity" : 0,
         "position" : 0,
         "type" : 0 //static
      },
      
      {
         "angle" : 0,
         "angularVelocity" : 0,
         "awake" : true,
         "linearVelocity" : 0,
         "position" : 0,
         "type" : 0 //static
      },
      
      {
         "angle" : 0,
         "angularVelocity" : 0,
         "awake" : true,
         "linearVelocity" : 0,
         "position" : 0,
         "type" : 0 //static
      },
      
      {
         "angle" : 0,
         "angularVelocity" : 0,
         "awake" : true,
         "linearVelocity" : 0,
         "position" : 0,
         "type" : 0 //static
      },
      
      {
         "angle" : "C4159693",
         "angularVelocity" : "BF509A83",
         "awake" : true,
         "fixture" : 
         [
            
            {
               "circle" : 
               {
                  "center" : 
                  {
                     "x" : "3D1F5E40",
                     "y" : "3CC3F580"
                  },
                  "radius" : "40500AED"
               },
               "density" : "3F19999A",
               "friction" : "3E99999A",
               "restitution" : "3F4CCCCD"
            }
         ],
         "gravityScale" : "411CCCCD",
         "linearVelocity" : 
         {
            "x" : "3B5AFF1C",
            "y" : "C1C3E40F"
         },
         "massData-I" : "42D28DB2",
         "massData-center" : 
         {
            "x" : "3D1F5E40",
            "y" : "3CC3F580"
         },
         "massData-mass" : "419F5819",
         "position" : 
         {
            "x" : "405BD9EE",
            "y" : "41610A7A"
         },
         "type" : 2 //dynamic
      },
      
      {
         "angle" : "C41520CC",
         "angularVelocity" : "3FE4DF7E",
         "awake" : true,
         "fixture" : 
         [
            
            {
               "circle" : 
               {
                  "center" : 
                  {
                     "x" : "3C39E460",
                     "y" : "BC2F6460"
                  },
                  "radius" : "3FC44454"
               },
               "density" : "3F86B86E",
               "friction" : "3DCCCCCD",
               "restitution" : "3E99999A"
            }
         ],
         "gravityScale" : "411CCCCD",
         "linearVelocity" : 
         {
            "x" : "403C621D",
            "y" : "BD9D6207"
         },
         "massData-I" : "41124080",
         "massData-center" : 
         {
            "x" : "3C39E460",
            "y" : "BC2F6460"
         },
         "massData-mass" : "40F8C50E",
         "position" : 
         {
            "x" : "41FA5081",
            "y" : "41A782B9"
         },
         "type" : 2 //dynamic
      },
      
      {
         "angle" : "BBDE3018",
         "angularVelocity" : "BCA92924",
         "awake" : true,
         "fixture" : 
         [
            
            {
               "density" : "3F828F5C",
               "friction" : "3DCCCCCD",
               "polygon" : 
               {
                  "vertices" : 
                  {
                     "x" : [ "411093A3", "41108E8D", "C10BEB97", "C10BEB97" ],
                     "y" : [ "BE5163C0", "3E727440", "3E5F6840", "BE84B820" ]
                  }
               },
               "restitution" : "3E99999A"
            }
         ],
         "linearVelocity" : 
         {
            "x" : "40B4AD34",
            "y" : "BF3E82DB"
         },
         "massData-I" : "435B8175",
         "massData-center" : 
         {
            "x" : "3CEAABAC",
            "y" : "BB1F674D"
         },
         "massData-mass" : "410548E0",
         "position" : 
         {
            "x" : "41CAAED3",
            "y" : "4199C262"
         },
         "type" : 2 //dynamic
      },
      
      {
         "angle" : "BBFA576F",
         "angularVelocity" : "3D938634",
         "awake" : true,
         "fixture" : 
         [
            
            {
               "density" : "3F828F5C",
               "friction" : "3DCCCCCD",
               "polygon" : 
               {
                  "vertices" : 
                  {
                     "x" : [ "41114A01", "411144E9", "C10BB952", "C10BB952" ],
                     "y" : [ "BE3DB9FA", "3E8377EA", "3E73DAFC", "BE75E080" ]
                  }
               },
               "restitution" : "3E99999A"
            }
         ],
         "linearVelocity" : 
         {
            "x" : "3E50FB7B",
            "y" : "BF37763A"
         },
         "massData-I" : "435D2005",
         "massData-center" : 
         {
            "x" : "3D68C927",
            "y" : "3C8C61D6"
         },
         "massData-mass" : "4105C4C3",
         "position" : 
         {
            "x" : "41B456ED",
            "y" : "41B5B78C"
         },
         "type" : 2 //dynamic
      },
      
      {
         "angle" : "C41520B3",
         "angularVelocity" : "3FE5D81D",
         "awake" : true,
         "fixture" : 
         [
            
            {
               "circle" : 
               {
                  "center" : 
                  {
                     "x" : "3CA45C7A",
                     "y" : "3CAF3128"
                  },
                  "radius" : "3FC4CC15"
               },
               "density" : "3F86B86E",
               "friction" : "3DCCCCCD",
               "restitution" : "3E99999A"
            }
         ],
         "gravityScale" : "411CCCCD",
         "linearVelocity" : 
         {
            "x" : "403A74C0",
            "y" : "BF852124"
         },
         "massData-I" : "4113EA7A",
         "massData-center" : 
         {
            "x" : "3CA45C7A",
            "y" : "3CAF3128"
         },
         "massData-mass" : "40FA1DA9",
         "position" : 
         {
            "x" : "4186582E",
            "y" : "41A7C102"
         },
         "type" : 2 //dynamic
      },
      
      {
         "angle" : "C41592C9",
         "angularVelocity" : "BFADE4E6",
         "awake" : true,
         "fixture" : 
         [
            
            {
               "circle" : 
               {
                  "center" : 
                  {
                     "x" : "3BB34380",
                     "y" : "BB23EF00"
                  },
                  "radius" : "4022F4E6"
               },
               "density" : "3F86B86E",
               "friction" : "3DCCCCCD",
               "restitution" : "3E99999A"
            }
         ],
         "gravityScale" : "411CCCCD",
         "linearVelocity" : 
         {
            "x" : "405C2C36",
            "y" : "BEFCA00A"
         },
         "massData-I" : "428AFA68",
         "massData-center" : 
         {
            "x" : "3BB34380",
            "y" : "BB23EF00"
         },
         "massData-mass" : "41AB7E52",
         "position" : 
         {
            "x" : "4197A9D4",
            "y" : "4183EF35"
         },
         "type" : 2 //dynamic
      },
      
      {
         "angle" : "C4159764",
         "angularVelocity" : "BFC826CB",
         "awake" : true,
         "fixture" : 
         [
            
            {
               "circle" : 
               {
                  "center" : 
                  {
                     "x" : "3BC0FCCF",
                     "y" : "BAE4A064"
                  },
                  "radius" : "4022F616"
               },
               "density" : "3F86B86E",
               "friction" : "3DCCCCCD",
               "restitution" : "3E99999A"
            }
         ],
         "gravityScale" : "411CCCCD",
         "linearVelocity" : 
         {
            "x" : "4079E108",
            "y" : "BF582E75"
         },
         "massData-I" : "428AFE79",
         "massData-center" : 
         {
            "x" : "3BC0FCCF",
            "y" : "BAE4A064"
         },
         "massData-mass" : "41AB80D2",
         "position" : 
         {
            "x" : "41DF9437",
            "y" : "41838BB5"
         },
         "type" : 2 //dynamic
      },
      
      {
         "angle" : 0,
         "angularVelocity" : 0,
         "awake" : true,
         "fixture" : 
         [
            
            {
               "density" : "40400000",
               "friction" : "3ECCCCCD",
               "polygon" : 
               {
                  "vertices" : 
                  {
                     "x" : [ "3FD476CC", "BFC31B0C", "BFC08A62", "3FD1ECF0" ],
                     "y" : [ "4077B380", "40780CB8", "C076809A", "C07808B4" ]
                  }
               },
               "restitution" : "3DCCCCCD"
            }
         ],
         "linearVelocity" : 0,
         "position" : 
         {
            "x" : "41CBCD21",
            "y" : "41223A19"
         },
         "type" : 0 //static
      },
      
      {
         "angle" : 0,
         "angularVelocity" : 0,
         "awake" : true,
         "linearVelocity" : 0,
         "position" : 0,
         "type" : 0 //static
      },
      
      {
         "angle" : "C416046D",
         "angularVelocity" : "BF814D95",
         "awake" : true,
         "fixture" : 
         [
            
            {
               "circle" : 
               {
                  "center" : 
                  {
                     "x" : "3C913200",
                     "y" : "BCABFD00"
                  },
                  "radius" : "3FF3D854"
               },
               "density" : "3F86B86E",
               "friction" : "3E99999A",
               "restitution" : "3F4CCCCD"
            }
         ],
         "gravityScale" : "411CCCCD",
         "linearVelocity" : 
         {
            "x" : "400DBBC2",
            "y" : "C0827EE6"
         },
         "massData-I" : "41AE45DA",
         "massData-center" : 
         {
            "x" : "3C913200",
            "y" : "BCABFD00"
         },
         "massData-mass" : "41400000",
         "name" : "mouse",
         "position" : 
         {
            "x" : "41DDC0CB",
            "y" : "41C60E9B"
         },
         "type" : 2 //dynamic
      },
      
      {
         "angle" : 0,
         "angularVelocity" : 0,
         "awake" : true,
         "fixture" : 
         [
            
            {
               "density" : "40400000",
               "friction" : "3ECCCCCD",
               "polygon" : 
               {
                  "vertices" : 
                  {
                     "x" : [ "3FCFF450", "3FCEECFC", "BFC143EC", "BFC08A62" ],
                     "y" : [ "C0768098", "407A6F90", "4079B4BC", "C076809A" ]
                  }
               },
               "restitution" : "3DCCCCCD"
            }
         ],
         "gravityScale" : "411CCCCD",
         "linearVelocity" : 0,
         "position" : 
         {
            "x" : "41854861",
            "y" : "4121BBDB"
         },
         "type" : 0 //static
      },
      
      {
         "angle" : "4309CF35",
         "angularVelocity" : "3C48E401",
         "awake" : true,
         "fixture" : 
         [
            
            {
               "circle" : 
               {
                  "center" : 
                  {
                     "x" : "3C913200",
                     "y" : "BCABFD00"
                  },
                  "radius" : "3FF3D854"
               },
               "density" : "3FCA14A5",
               "friction" : "3E99999A",
               "restitution" : "3F4CCCCD"
            }
         ],
         "gravityScale" : "411CCCCD",
         "linearVelocity" : 
         {
            "x" : "BCBF42AD",
            "y" : "3FA740DB"
         },
         "massData-I" : "4202B464",
         "massData-center" : 
         {
            "x" : "3C913200",
            "y" : "BCABFD00"
         },
         "massData-mass" : "41900000",
         "name" : "snake",
         "position" : 
         {
            "x" : "BDA1217A",
            "y" : "40089DDB"
         },
         "type" : 2 //dynamic
      },
      
      {
         "angle" : 0,
         "angularVelocity" : 0,
         "awake" : true,
         "fixture" : 
         [
            
            {
               "density" : "41200000",
               "edge" : 
               {
                  "vertex1" : 
                  {
                     "x" : "C1BFE42D",
                     "y" : "BD6DBCBA"
                  },
                  "vertex2" : 
                  {
                     "x" : "41BFCDC6",
                     "y" : "BD6DBCBA"
                  }
               },
               "friction" : "3E99999A",
               "restitution" : "3F333333"
            }
         ],
         "linearVelocity" : 0,
         "position" : 
         {
            "x" : "41A237E1",
            "y" : "3E6CD600"
         },
         "type" : 0 //static
      },
      
      {
         "angle" : 0,
         "angularVelocity" : 0,
         "awake" : true,
         "fixture" : 
         [
            
            {
               "density" : "41200000",
               "edge" : 
               {
                  "vertex1" : 
                  {
                     "x" : "C1BFEBFB",
                     "y" : "BD7431C0"
                  },
                  "vertex2" : 
                  {
                     "x" : "41BFD5B8",
                     "y" : "BD7431C0"
                  }
               },
               "friction" : "3E99999A",
               "restitution" : "3F333333"
            }
         ],
         "linearVelocity" : 0,
         "position" : 
         {
            "x" : "41A26523",
            "y" : "42008FEC"
         },
         "type" : 0 //static
      },
      
      {
         "angle" : "3FC90FDB",
         "angularVelocity" : 0,
         "awake" : true,
         "fixture" : 
         [
            
            {
               "density" : "41200000",
               "edge" : 
               {
                  "vertex1" : 
                  {
                     "x" : "C17FB944",
                     "y" : "BD8DAC40"
                  },
                  "vertex2" : 
                  {
                     "x" : "417F12D4",
                     "y" : "BD8DAC40"
                  }
               },
               "friction" : "3E99999A",
               "restitution" : "3F333333"
            }
         ],
         "linearVelocity" : 0,
         "position" : 
         {
            "x" : "C0709652",
            "y" : "4181323D"
         },
         "type" : 0 //static
      },
      
      {
         "angle" : "3FC90FDB",
         "angularVelocity" : 0,
         "awake" : true,
         "fixture" : 
         [
            
            {
               "density" : "41200000",
               "edge" : 
               {
                  "vertex1" : 
                  {
                     "x" : "C17FB944",
                     "y" : "BD8DAC40"
                  },
                  "vertex2" : 
                  {
                     "x" : "417F12D4",
                     "y" : "BD8DAC40"
                  }
               },
               "friction" : "3E99999A",
               "restitution" : "3F333333"
            }
         ],
         "linearVelocity" : 0,
         "position" : 
         {
            "x" : "4230DFF8",
            "y" : "4181323D"
         },
         "type" : 0 //static
      },
      
      {
         "angle" : 0,
         "angularVelocity" : 0,
         "awake" : true,
         "linearVelocity" : 0,
         "position" : 0,
         "type" : 0 //static
      },
      
      {
         "angle" : 0,
         "angularVelocity" : 0,
         "awake" : true,
         "linearVelocity" : 0,
         "position" : 0,
         "type" : 0 //static
      },
      
      {
         "angle" : "3FD90A8E",
         "angularVelocity" : "BF329879",
         "awake" : true,
         "fixture" : 
         [
            
            {
               "density" : "3F828F5C",
               "friction" : "3F19999A",
               "polygon" : 
               {
                  "vertices" : 
                  {
                     "x" : [ "3EB206F0", "BEE13188", "BEB8E990", "3E9A73B0" ],
                     "y" : [ "40872ADC", "408704A2", "C08EFE56", "C08F0902" ]
                  }
               },
               "restitution" : "3E99999A"
            }
         ],
         "linearVelocity" : 
         {
            "x" : "BFB12464",
            "y" : "4009A116"
         },
         "massData-I" : "42229FD5",
         "massData-center" : 
         {
            "x" : "BD1C0CB9",
            "y" : "3A4FE925"
         },
         "massData-mass" : "40CDB659",
         "position" : 
         {
            "x" : "404453DB",
            "y" : "40AAE6FD"
         },
         "type" : 2 //dynamic
      },
      
      {
         "angle" : "BE91A96F",
         "angularVelocity" : "3D2A537C",
         "awake" : true,
         "fixture" : 
         [
            
            {
               "density" : "3F828F5C",
               "friction" : "3F19999A",
               "polygon" : 
               {
                  "vertices" : 
                  {
                     "x" : [ "3EA867F0", "3E810930", "BEA66748", "BEB8E990" ],
                     "y" : [ "C0C0C199", "411F231F", "411F1003", "C0C0E092" ]
                  }
               },
               "restitution" : "3E99999A"
            }
         ],
         "linearVelocity" : 
         {
            "x" : "3F9832E4",
            "y" : "BFF1E311"
         },
         "massData-I" : "4379AC64",
         "massData-center" : 
         {
            "x" : "BCD4F844",
            "y" : "3FDC5F7B"
         },
         "massData-mass" : "41251DE8",
         "position" : 
         {
            "x" : "41A98535",
            "y" : "40DB1AE3"
         },
         "type" : 2 //dynamic
      },
      
      {
         "angle" : 0,
         "angularVelocity" : 0,
         "awake" : true,
         "linearVelocity" : 0,
         "position" : 0,
         "type" : 0 //static
      },
      
      {
         "angle" : 0,
         "angularVelocity" : 0,
         "awake" : true,
         "linearVelocity" : 0,
         "position" : 0,
         "type" : 0 //static
      },
      
      {
         "angle" : 0,
         "angularVelocity" : 0,
         "awake" : true,
         "linearVelocity" : 0,
         "position" : 
         {
            "x" : "405E6D40",
            "y" : "4160E3D8"
         },
         "type" : 0 //static
      },
      
      {
         "angle" : 0,
         "angularVelocity" : 0,
         "awake" : true,
         "linearVelocity" : 0,
         "position" : 0,
         "type" : 0 //static
      },
      
      {
         "angle" : 0,
         "angularVelocity" : 0,
         "awake" : true,
         "linearVelocity" : 0,
         "position" : 
         {
            "x" : "4048B8C6",
            "y" : "40A12277"
         },
         "type" : 0 //static
      },
      
      {
         "angle" : 0,
         "angularVelocity" : 0,
         "awake" : true,
         "linearVelocity" : 0,
         "position" : 
         {
            "x" : "41A95B67",
            "y" : "40DCFA56"
         },
         "type" : 0 //static
      },
      
      {
         "angle" : 0,
         "angularVelocity" : 0,
         "awake" : true,
         "linearVelocity" : 0,
         "position" : 0,
         "type" : 0 //static
      },
      
      {
         "angle" : 0,
         "angularVelocity" : 0,
         "awake" : true,
         "linearVelocity" : 0,
         "position" : 0,
         "type" : 0 //static
      }
   ],
   "continuousPhysics" : true,
   "gravity" : 
   {
      "x" : 0,
      "y" : "C1200000"
   },
   "joint" : 
   [
      
      {
         "anchorA" : 
         {
            "x" : "3C124500",
            "y" : "BC124400"
         },
         "anchorB" : 
         {
            "x" : "3CC5C962",
            "y" : "3D3EE05E"
         },
         "bodyA" : 28,
         "bodyB" : 6,
         "dampingRatio" : 0,
         "frequency" : 0,
         "length" : 0,
         "type" : "distance"
      },
      
      {
         "anchorA" : 
         {
            "x" : "BDB09C8E",
            "y" : "C0885A4B"
         },
         "anchorB" : 
         {
            "x" : "BDB0F05C",
            "y" : "C0B645A8"
         },
         "bodyA" : 24,
         "bodyB" : 25,
         "collideConnected" : true,
         "maxLength" : "418EEF61",
         "type" : "rope"
      },
      
      {
         "anchorA" : 
         {
            "x" : "BD7EE961",
            "y" : "BDCB2234"
         },
         "anchorB" : 
         {
            "x" : "3D5FA600",
            "y" : "3E5FA5A0"
         },
         "bodyA" : 24,
         "bodyB" : 30,
         "dampingRatio" : 0,
         "frequency" : "7F7FFFFF",
         "length" : 0,
         "type" : "distance"
      },
      
      {
         "anchorA" : 0,
         "anchorB" : 
         {
            "x" : "3A5BD7F1",
            "y" : "3D83E528"
         },
         "bodyA" : 31,
         "bodyB" : 25,
         "collideConnected" : true,
         "dampingRatio" : 0,
         "frequency" : "7F7FFFFF",
         "length" : "3CAC3223",
         "type" : "distance"
      }
   ],
   "subStepping" : false,
   "warmStarting" : true
}
